{"classification": "AI-generated", "confidence": 51.46030134068034, "ai_probability": 51.46030134068034, "human_probability": 48.53969865931966, "chunk_details": [{"chunk_id": 1, "text": "s options can be passed via data attributes or javascript you can append an option name to databs as...", "ai_probability": 51.46030134068034, "human_probability": 48.53969865931966}], "note": "This is a simulated result as the real model is not available.", "timestamp": "2025-04-12T05:11:46.048731", "analysis_id": "46241781-24a7-4ae4-953b-2224ac55aa5a"}