{"classification": "AI-generated", "confidence": 50.661615444095176, "ai_probability": 50.661615444095176, "human_probability": 49.338384555904824, "chunk_details": [{"chunk_id": 1, "text": "love and greed are two powerful emotions that influence human behavior and relationships while love ...", "ai_probability": 58.939915502845494, "human_probability": 41.060084497154506}, {"chunk_id": 2, "text": "recent years the world has witnessed a growing awareness of the impact of greed especially in light ...", "ai_probability": 42.383315385344865, "human_probability": 57.616684614655135}], "note": "This is a simulated result as the real model is not available.", "timestamp": "2025-03-18T06:20:44.398395", "analysis_id": "86a2e1b9-de9b-4354-b680-1d8a1b41b941"}