{"classification": "Human-written", "confidence": 55.44605331580461, "ai_probability": 44.55394668419538, "human_probability": 55.44605331580461, "chunk_details": [{"chunk_id": 1, "text": "the documentary mga lihim ng pamilya ni rizal presents a compelling investigation into the alberto m...", "ai_probability": 58.92280361011546, "human_probability": 41.07719638988454}, {"chunk_id": 2, "text": "gain new perspectives on how individual lives intersect with broader historical currents and how per...", "ai_probability": 30.185089758275307, "human_probability": 69.81491024172469}], "note": "This is a simulated result as the real model is not available.", "timestamp": "2025-03-26T07:04:18.174299", "analysis_id": "8e9c2612-f40b-43e7-97e5-d102df8292eb"}