{"classification": "Human-written", "confidence": 62.486756700352885, "ai_probability": 37.51324329964712, "human_probability": 62.486756700352885, "chunk_details": [{"chunk_id": 1, "text": "as a secondyear broadcasting student technology has become an indispensable part of my daily academi...", "ai_probability": 37.51324329964712, "human_probability": 62.486756700352885}], "note": "This is a simulated result as the real model is not available.", "timestamp": "2025-03-25T05:54:45.952541", "analysis_id": "e12447df-1269-46dc-9e49-ad42131259bd"}