{"classification": "Human-written", "confidence": 54.468885879359185, "ai_probability": 45.531114120640815, "human_probability": 54.468885879359185, "chunk_details": [{"chunk_id": 1, "text": "love and greed are two powerful emotions that influence human behavior and relationships while love ...", "ai_probability": 37.47200879319369, "human_probability": 62.52799120680632}, {"chunk_id": 2, "text": "recent years the world has witnessed a growing awareness of the impact of greed especially in light ...", "ai_probability": 53.59021944808795, "human_probability": 46.40978055191205}], "note": "This is a simulated result as the real model is not available.", "timestamp": "2025-03-18T06:22:57.564932", "analysis_id": "f9d80a36-320f-465a-8106-2b6162978829"}